README.md
setup.cfg
setup.py
distributions/Binomialdistribution.py
distributions/Gaussiandistribution.py
distributions/Generaldistribution.py
distributions/__init__.py
dsnd_probability_ale.egg-info/PKG-INFO
dsnd_probability_ale.egg-info/SOURCES.txt
dsnd_probability_ale.egg-info/dependency_links.txt
dsnd_probability_ale.egg-info/not-zip-safe
dsnd_probability_ale.egg-info/top_level.txt