Metadata-Version: 1.0
Name: dsnd-probability-ale
Version: 1.0
Summary: Gaussian and Binomialdistributions
Home-page: UNKNOWN
Author: Alejandro Rios
Author-email: aarc.88@gmail.com
License: UNKNOWN
Platform: UNKNOWN
